dashpool_components
dashpool_components_base
