Metadata-Version: 2.1
Name: dashpool-components
Version: 0.1.9
Summary: Custom Components for Dashpool
Home-page: https://github.com/dashpool
Author: Viktor Krückl <viktor@krueckl.de>
License: MIT
Platform: UNKNOWN
Classifier: Framework :: Dash
License-File: LICENSE
